{
	"site_name": "Sendit",
	"site_title": "Sendit Template Astro",
	"description": "A polished, marketing website template built with Astro.",
	"author": "",
	"author_email": "",
	"images": [
		{
			"image": "/images/_screenshot.png",
			"description": "Screenshot for Sendit Template",
			"height": 0,
			"width": 0
		}
	],
	"_structures": {
		"images": {
			"style": "select",
			"values": [
				{
					"label": "Image",
					"icon": "image",
					"value": {
						"image": "",
						"description": "",
						"height": 0,
						"width": 0
					}
				}
			]
		}
	}
}
